{
  "Tasks": [
    {
      "id": 1,
      "label": "Learn Angular",
      "completed": false
    },
    {
      "id": 3,
      "label": "Learn Symfony",
      "completed": false
    },
    {
      "id": 4,
      "label": "Learn Bootstrap",
      "completed": true
    },
    {
      "id": 6,
      "label": "Learn ReactJs",
      "completed": true
    },
    {
      "label": "Learn Xamarin",
      "completed": true,
      "id": 7
    },
    {
      "label": "Learn AJAX",
      "completed": false,
      "id": 8
    }
  ]
}